<?xml version = '1.0' encoding = 'UTF-8'?>
<TableProxyOraclev11g class="oracle.dbtools.crest.model.design.storage.oracle.v11g.TableProxyOraclev11g" name="Placanje" directorySegmentName="seg_0" id="7492CEBC-24A9-5BDE-253C-A7E9BDF0B055">
<createdBy>bojan</createdBy>
<createdTime>2024-12-02 15:56:43 UTC</createdTime>
<ownerDesignName>Projekat</ownerDesignName>
<logging>YES</logging>
<partitionedRowMovement>DISABLE</partitionedRowMovement>
<temporaryChanged>false</temporaryChanged>
<accessDriverType>oracle_loader</accessDriverType>
<rejectLimit></rejectLimit>
<columnProxies itemClass="oracle.dbtools.crest.model.design.storage.oracle.v12c.ColumnProxyOraclev12c">
<ColumnProxy name="ID_Prodaje" id="1E320215-9776-7913-55E3-0D75B5827126">
<createdBy>bojan</createdBy>
<createdTime>2024-12-02 15:56:43 UTC</createdTime>
<ownerDesignName>Projekat</ownerDesignName>
</ColumnProxy>
<ColumnProxy name="Iznos" id="450ADFD6-E500-F7C1-84D9-822E9AF4D906">
<createdBy>bojan</createdBy>
<createdTime>2024-12-02 15:56:43 UTC</createdTime>
<ownerDesignName>Projekat</ownerDesignName>
</ColumnProxy>
<ColumnProxy name="Tip_Placanja" id="7A660BE4-1EB4-C04E-A5B0-28D4579905D0">
<createdBy>bojan</createdBy>
<createdTime>2024-12-02 15:56:43 UTC</createdTime>
<ownerDesignName>Projekat</ownerDesignName>
</ColumnProxy>
<ColumnProxy name="ID_Placanja" id="96E45B16-83D5-9750-32B0-0E438ACA343C">
<createdBy>bojan</createdBy>
<createdTime>2024-12-02 15:56:43 UTC</createdTime>
<ownerDesignName>Projekat</ownerDesignName>
</ColumnProxy>
</columnProxies>
<foreignKeys>
<ForeignKey class="oracle.dbtools.crest.model.design.storage.oracle.v10g.FKProxyOraclev10g" name="Placanje_Prodaja_FK" id="3AAEA483-0EA6-0E9C-6E92-DC2ED9A7FB35">
<createdBy>bojan</createdBy>
<createdTime>2024-12-02 15:56:43 UTC</createdTime>
<ownerDesignName>Projekat</ownerDesignName>
</ForeignKey>
</foreignKeys>
<primaryKeys>
<PrimaryKey class="oracle.dbtools.crest.model.design.storage.oracle.v10g.PKProxyOraclev10g" name="Placanje_PK" id="FC4CB1AD-2B95-986F-3A97-4C831D40C2B8">
<createdBy>bojan</createdBy>
<createdTime>2024-12-02 15:56:43 UTC</createdTime>
<ownerDesignName>Projekat</ownerDesignName>
<indexSort>SORTED</indexSort>
</PrimaryKey>
</primaryKeys>
</TableProxyOraclev11g>