<?xml version = '1.0' encoding = 'UTF-8'?>
<FKIndexAssociation class="oracle.dbtools.crest.model.design.relational.FKIndexAssociation" directorySegmentName="seg_0" id="ECE72331-DC2F-8E60-D853-ED1970AD84B2" containerWithKeyObject="3FA58D8D-EA84-9632-AC7E-1B59E3A4D593" localFKIndex="BB3DD4C1-DEDC-9494-B104-4BC9D24D485C" name="Cena_Vozilo_FK">
<createdBy>djradovic</createdBy>
<createdTime>2024-12-09 19:42:08 UTC</createdTime>
<ownerDesignName>Projekat</ownerDesignName>
<referredTableLongName>Vozilo</referredTableLongName>
<deleteRule>NO ACTION</deleteRule>
<referredTableID>2ED0A908-1FFB-33A8-745B-6C74C4A982A8</referredTableID>
<keyObject>E4968490-0553-232E-0F6A-FD783BF93CD0</keyObject>
<referredKeyID>E4968490-0553-232E-0F6A-FD783BF93CD0</referredKeyID>
<mandatory>true</mandatory>
<refColNames>ID_Vozila</refColNames>
<transferable>true</transferable>
<rely>false</rely>
<columnDependencyConstraintGenerateInDDL>true</columnDependencyConstraintGenerateInDDL>
</FKIndexAssociation>
